setup.py
dachkovski_probability/Binomialdistribution.py
dachkovski_probability/Gaussiandistribution.py
dachkovski_probability/Generaldistribution.py
dachkovski_probability/__init__.py
dachkovski_probability.egg-info/PKG-INFO
dachkovski_probability.egg-info/SOURCES.txt
dachkovski_probability.egg-info/dependency_links.txt
dachkovski_probability.egg-info/not-zip-safe
dachkovski_probability.egg-info/top_level.txt