Metadata-Version: 1.0
Name: dachkovski-probability
Version: 1.0
Summary: Gaussian and Binomial distributions
Home-page: UNKNOWN
Author: Dennis Dachkovski
Author-email: dennis@dachkovski.de
License: UNKNOWN
Platform: UNKNOWN
